installed_packages_diff/__init__.py
installed_packages_diff/__main__.py
installed_packages_diff/config.py
installed_packages_diff/differ.py
installed_packages_diff/fetcher.py
installed_packages_diff/local_transport.py
installed_packages_diff/main.py
installed_packages_diff/package.py
installed_packages_diff/printing.py
installed_packages_diff/ssh_transport.py
installed_packages_diff/transport.py
installed_packages_diff/transport_factory.py
installed_packages_diff-3.1.0.dist-info/METADATA
installed_packages_diff-3.1.0.dist-info/WHEEL
installed_packages_diff-3.1.0.dist-info/namespace_packages.txt
installed_packages_diff-3.1.0.dist-info/top_level.txt
installed_packages_diff-3.1.0.dist-info/RECORD
