Metadata-Version: 2.1
Name: installed-packages-diff
Version: 3.1.0
Summary: Compare packages and versions on servers
Home-page: https://github.com/cbuschka/installed-packages-diff
Author: Cornelius Buschka
Author-email: cbuschka@gmail.com
License: MIT License
Platform: Posix; MacOS X
Classifier: Development Status :: 5 - Production/Stable
Classifier: Intended Audience :: Developers
Classifier: License :: OSI Approved :: MIT License
Classifier: Operating System :: OS Independent
Classifier: Programming Language :: Python :: 3
Classifier: Programming Language :: Python :: 3.6
Classifier: Programming Language :: Python :: 3.7
Classifier: Programming Language :: Python :: 3.8
Classifier: Programming Language :: Python :: 3.9
Classifier: Topic :: System :: Software Distribution
Requires-Python: >= 3.6
Requires-Dist: paramiko (>=2.7.2)
Requires-Dist: pyyaml (>=5.4.1)
Requires-Dist: jsonschema (>=3.2.0)
